precisenumbers/__init__.py
precisenumbers/coordinates.py
tests/__init__.py
tests/test_coordinates.py
tests/test_precisenumbers.py
precisenumbers-1.0.1.dist-info/LICENSE
precisenumbers-1.0.1.dist-info/METADATA
precisenumbers-1.0.1.dist-info/WHEEL
precisenumbers-1.0.1.dist-info/top_level.txt
precisenumbers-1.0.1.dist-info/RECORD
