Metadata-Version: 2.1
Name: precisenumbers
Version: 1.0.1
Summary: For when you want your numbers to be precise
Home-page: https://github.com/ricklentz/precisenumbers
License-File: LICENSE
